odoo/addons/photovoltaic_production/__init__.py
odoo/addons/photovoltaic_production/__manifest__.py
odoo/addons/photovoltaic_production/i18n/es.po
odoo/addons/photovoltaic_production/i18n/photovoltaic_production.pot
odoo/addons/photovoltaic_production/models/__init__.py
odoo/addons/photovoltaic_production/models/photovoltaic_power_station.py
odoo/addons/photovoltaic_production/models/photovoltaic_production.py
odoo/addons/photovoltaic_production/models/photovoltaic_production_bill.py
odoo/addons/photovoltaic_production/models/photovoltaic_production_power_station_order.py
odoo/addons/photovoltaic_production/models/photovoltaic_production_regularization.py
odoo/addons/photovoltaic_production/security/ir.model.access.csv
odoo/addons/photovoltaic_production/static/description/icon.png
odoo/addons/photovoltaic_production/views/photovoltaic_power_station.xml
odoo/addons/photovoltaic_production/views/photovoltaic_production.xml
odoo/addons/photovoltaic_production/views/photovoltaic_production_bill.xml
odoo/addons/photovoltaic_production/views/photovoltaic_production_power_station_order.xml
odoo/addons/photovoltaic_production/views/photovoltaic_production_regularization.xml
odoo/addons/photovoltaic_production/wizard/__init__.py
odoo/addons/photovoltaic_production/wizard/export_csv_wizard.py
odoo/addons/photovoltaic_production/wizard/export_csv_wizard.xml
odoo13_addon_photovoltaic_production-13.0.1.2.4.dist-info/METADATA
odoo13_addon_photovoltaic_production-13.0.1.2.4.dist-info/WHEEL
odoo13_addon_photovoltaic_production-13.0.1.2.4.dist-info/top_level.txt
odoo13_addon_photovoltaic_production-13.0.1.2.4.dist-info/RECORD
