Metadata-Version: 2.1
Name: odoo13-addon-photovoltaic_production
Version: 13.0.1.2.4
Requires-Python: >=3.5
Requires-Dist: odoo13-addon-web_tree_dynamic_colored_field
Requires-Dist: odoo>=13.0a,<13.1dev
Requires-Dist: python-dateutil
Summary: Photovoltaic Production
Author: Librecoop
Classifier: Programming Language :: Python
Classifier: Framework :: Odoo
Classifier: Framework :: Odoo :: 13.0
